{
  "get_nzh_requestSettlement": {
    "platform_url": "base_url",
    "sub_url": "/nzh/doServiceCall",
    "http_verb": "post",
    "products": {
      "production": 29986,
      "sandbox": 39372
    }
  },
  "get_nzh_biz_requestSettlement": {
    "platform_url": "base_url",
    "sub_url": "/nzh/doServiceCall",
    "http_verb": "post",
    "products": {
      "production": 29987,
      "sandbox": 39373
    }
  },
  "get_nzh_biz_requestSettlementByTool": {
    "platform_url": "base_url",
    "sub_url": "/nzh/doServiceCall",
    "http_verb": "post",
    "products": {
      "production": 29988,
      "sandbox": 39374
    }
  },
  "get_nzh_listSettlements": {
    "platform_url": "base_url",
    "sub_url": "/nzh/doServiceCall",
    "http_verb": "post",
    "products": {
      "production": 29989,
      "sandbox": 39375
    }
  },
  "get_nzh_biz_addAutoSettlement": {
    "platform_url": "base_url",
    "sub_url": "/nzh/doServiceCall",
    "http_verb": "post",
    "products": {
      "production": 29990,
      "sandbox": 39376
    }
  },
  "get_nzh_biz_removeAutoSettlement": {
    "platform_url": "base_url",
    "sub_url": "/nzh/doServiceCall",
    "http_verb": "post",
    "products": {
      "production": 29991,
      "sandbox": 39377
    }
  }
}